{"data": [{"timestamp": "2024-07-29 21:43:50", "planta": "Planta 1", "compresor1": 1.0, "compresor2": 0.0, "temp1": 21.0, "humedad1": 59.4, "temp2": null, "humedad2": null, "pureza_oxigeno": 425.0, "presion_linea": 396.0, "caudal": 379.0}, {"timestamp": "2024-07-29 21:43:51", "planta": "Planta 1", "compresor1": 1.0, "compresor2": 0.0, "temp1": 21.0, "humedad1": 59.4, "temp2": null, "humedad2": null, "pureza_oxigeno": 334.0, "presion_linea": 334.0, "caudal": 329.0}, {"timestamp": "2024-07-29 21:43:52", "planta": "Planta 1", "compresor1": 1.0, "compresor2": 0.0, "temp1": 21.0, "humedad1": 59.6, "temp2": null, "humedad2": null, "pureza_oxigeno": 261.0, "presion_linea": 254.0, "caudal": 259.0}, {"timestamp": "2024-07-29 21:43:53", "planta": "Planta 1", "compresor1": 1.0, "compresor2": 0.0, "temp1": 21.0, "humedad1": 59.6, "temp2": null, "humedad2": null, "pureza_oxigeno": 258.0, "presion_linea": 256.0, "caudal": 258.0}, {"timestamp": "2024-07-29 21:43:54", "planta": "Planta 1", "compresor1": 1.0, "compresor2": 0.0, "temp1": 21.1, "humedad1": 58.9, "temp2": null, "humedad2": null, "pureza_oxigeno": 294.0, "presion_linea": 298.0, "caudal": 289.0}]}