[{"timestamp": "2024-07-30 16:49:38", "planta": "Planta 1", "compresor1": "En l\u00ednea", "compresor2": "Off", "temp_secador_1": 18.8, "humedad_secador_1": 75.7, "temp_secador_2": NaN, "humedad_secador_2": NaN, "pureza_oxigeno": 411.0, "presion_linea": 368.0, "caudal": 341.0}, {"timestamp": "2024-07-30 16:49:39", "planta": "Planta 1", "compresor1": "En l\u00ednea", "compresor2": "Off", "temp_secador_1": 18.8, "humedad_secador_1": 75.7, "temp_secador_2": NaN, "humedad_secador_2": NaN, "pureza_oxigeno": 306.0, "presion_linea": 302.0, "caudal": 303.0}, {"timestamp": "2024-07-30 16:49:40", "planta": "Planta 1", "compresor1": "En l\u00ednea", "compresor2": "Off", "temp_secador_1": 18.8, "humedad_secador_1": 75.6, "temp_secador_2": NaN, "humedad_secador_2": NaN, "pureza_oxigeno": 297.0, "presion_linea": 296.0, "caudal": 294.0}, {"timestamp": "2024-07-30 16:49:41", "planta": "Planta 1", "compresor1": "En l\u00ednea", "compresor2": "Off", "temp_secador_1": 18.8, "humedad_secador_1": 75.6, "temp_secador_2": NaN, "humedad_secador_2": NaN, "pureza_oxigeno": 285.0, "presion_linea": 285.0, "caudal": 284.0}, {"timestamp": "2024-07-30 16:49:42", "planta": "Planta 1", "compresor1": "En l\u00ednea", "compresor2": "Off", "temp_secador_1": 18.7, "humedad_secador_1": 75.7, "temp_secador_2": NaN, "humedad_secador_2": NaN, "pureza_oxigeno": 290.0, "presion_linea": 292.0, "caudal": 289.0}, {"timestamp": "2024-07-30 16:49:43", "planta": "Planta 1", "compresor1": "En l\u00ednea", "compresor2": "Off", "temp_secador_1": 18.7, "humedad_secador_1": 75.7, "temp_secador_2": NaN, "humedad_secador_2": NaN, "pureza_oxigeno": 290.0, "presion_linea": 291.0, "caudal": 288.0}, {"timestamp": "2024-07-30 16:49:44", "planta": "Planta 1", "compresor1": "En l\u00ednea", "compresor2": "Off", "temp_secador_1": 18.8, "humedad_secador_1": 75.7, "temp_secador_2": NaN, "humedad_secador_2": NaN, "pureza_oxigeno": 282.0, "presion_linea": 282.0, "caudal": 280.0}, {"timestamp": "2024-07-30 16:49:45", "planta": "Planta 1", "compresor1": "En l\u00ednea", "compresor2": "Off", "temp_secador_1": 18.8, "humedad_secador_1": 75.7, "temp_secador_2": NaN, "humedad_secador_2": NaN, "pureza_oxigeno": 289.0, "presion_linea": 290.0, "caudal": 288.0}, {"timestamp": "2024-07-30 16:49:46", "planta": "Planta 1", "compresor1": "En l\u00ednea", "compresor2": "Off", "temp_secador_1": 18.9, "humedad_secador_1": 75.7, "temp_secador_2": NaN, "humedad_secador_2": NaN, "pureza_oxigeno": 282.0, "presion_linea": 282.0, "caudal": 280.0}, {"timestamp": "2024-07-30 16:49:47", "planta": "Planta 1", "compresor1": "En l\u00ednea", "compresor2": "Off", "temp_secador_1": 18.9, "humedad_secador_1": 75.7, "temp_secador_2": NaN, "humedad_secador_2": NaN, "pureza_oxigeno": 281.0, "presion_linea": 281.0, "caudal": 280.0}, {"timestamp": "2024-07-30 16:49:48", "planta": "Planta 1", "compresor1": "En l\u00ednea", "compresor2": "Off", "temp_secador_1": 18.8, "humedad_secador_1": 75.6, "temp_secador_2": NaN, "humedad_secador_2": NaN, "pureza_oxigeno": 288.0, "presion_linea": 289.0, "caudal": 285.0}, {"timestamp": "2024-07-30 16:49:49", "planta": "Planta 1", "compresor1": "En l\u00ednea", "compresor2": "Off", "temp_secador_1": 18.8, "humedad_secador_1": 75.6, "temp_secador_2": NaN, "humedad_secador_2": NaN, "pureza_oxigeno": 282.0, "presion_linea": 281.0, "caudal": 280.0}, {"timestamp": "2024-07-30 16:49:50", "planta": "Planta 1", "compresor1": "En l\u00ednea", "compresor2": "Off", "temp_secador_1": 18.8, "humedad_secador_1": 75.4, "temp_secador_2": NaN, "humedad_secador_2": NaN, "pureza_oxigeno": 290.0, "presion_linea": 292.0, "caudal": 289.0}, {"timestamp": "2024-07-30 16:49:51", "planta": "Planta 1", "compresor1": "En l\u00ednea", "compresor2": "Off", "temp_secador_1": 18.8, "humedad_secador_1": 75.4, "temp_secador_2": NaN, "humedad_secador_2": NaN, "pureza_oxigeno": 289.0, "presion_linea": 290.0, "caudal": 288.0}, {"timestamp": "2024-07-30 16:57:54", "planta": "Planta 1", "compresor1": "En l\u00ednea", "compresor2": "Off", "temp_secador_1": 18.8, "humedad_secador_1": 75.7, "temp_secador_2": NaN, "humedad_secador_2": NaN, "pureza_oxigeno": 279.0, "presion_linea": 279.0, "caudal": 277.0}, {"timestamp": "2024-07-30 16:57:54", "planta": "Planta 1", "compresor1": "En l\u00ednea", "compresor2": "Off", "temp_secador_1": 18.8, "humedad_secador_1": 75.7, "temp_secador_2": NaN, "humedad_secador_2": NaN, "pureza_oxigeno": 281.0, "presion_linea": 282.0, "caudal": 280.0}, {"timestamp": "2024-07-30 16:57:54", "planta": "Planta 1", "compresor1": "En l\u00ednea", "compresor2": "Off", "temp_secador_1": 18.8, "humedad_secador_1": 75.9, "temp_secador_2": NaN, "humedad_secador_2": NaN, "pureza_oxigeno": 288.0, "presion_linea": 289.0, "caudal": 286.0}, {"timestamp": "2024-07-30 16:57:54", "planta": "Planta 1", "compresor1": "En l\u00ednea", "compresor2": "Off", "temp_secador_1": 18.8, "humedad_secador_1": 75.7, "temp_secador_2": NaN, "humedad_secador_2": NaN, "pureza_oxigeno": 279.0, "presion_linea": 279.0, "caudal": 277.0}, {"timestamp": "2024-07-30 16:57:54", "planta": "Planta 1", "compresor1": "En l\u00ednea", "compresor2": "Off", "temp_secador_1": 18.8, "humedad_secador_1": 75.7, "temp_secador_2": NaN, "humedad_secador_2": NaN, "pureza_oxigeno": 281.0, "presion_linea": 282.0, "caudal": 280.0}, {"timestamp": "2024-07-30 16:57:55", "planta": "Planta 1", "compresor1": "En l\u00ednea", "compresor2": "Off", "temp_secador_1": 18.8, "humedad_secador_1": 75.8, "temp_secador_2": NaN, "humedad_secador_2": NaN, "pureza_oxigeno": 410.0, "presion_linea": 368.0, "caudal": 340.0}, {"timestamp": "2024-07-30 16:57:56", "planta": "Planta 1", "compresor1": "En l\u00ednea", "compresor2": "Off", "temp_secador_1": 18.8, "humedad_secador_1": 75.8, "temp_secador_2": NaN, "humedad_secador_2": NaN, "pureza_oxigeno": 306.0, "presion_linea": 302.0, "caudal": 302.0}, {"timestamp": "2024-07-30 16:57:57", "planta": "Planta 1", "compresor1": "En l\u00ednea", "compresor2": "Off", "temp_secador_1": 18.8, "humedad_secador_1": 75.5, "temp_secador_2": NaN, "humedad_secador_2": NaN, "pureza_oxigeno": 296.0, "presion_linea": 295.0, "caudal": 293.0}, {"timestamp": "2024-07-30 16:57:58", "planta": "Planta 1", "compresor1": "En l\u00ednea", "compresor2": "Off", "temp_secador_1": 18.8, "humedad_secador_1": 75.5, "temp_secador_2": NaN, "humedad_secador_2": NaN, "pureza_oxigeno": 285.0, "presion_linea": 284.0, "caudal": 283.0}, {"timestamp": "2024-07-30 16:58:00", "planta": "Planta 1", "compresor1": "En l\u00ednea", "compresor2": "Off", "temp_secador_1": 18.8, "humedad_secador_1": 75.6, "temp_secador_2": NaN, "humedad_secador_2": NaN, "pureza_oxigeno": 286.0, "presion_linea": 287.0, "caudal": 285.0}, {"timestamp": "2024-07-30 16:58:01", "planta": "Planta 1", "compresor1": "En l\u00ednea", "compresor2": "Off", "temp_secador_1": 18.8, "humedad_secador_1": 75.6, "temp_secador_2": NaN, "humedad_secador_2": NaN, "pureza_oxigeno": 292.0, "presion_linea": 294.0, "caudal": 291.0}, {"timestamp": "2024-07-30 16:58:02", "planta": "Planta 1", "compresor1": "En l\u00ednea", "compresor2": "Off", "temp_secador_1": 18.8, "humedad_secador_1": 75.6, "temp_secador_2": NaN, "humedad_secador_2": NaN, "pureza_oxigeno": 281.0, "presion_linea": 280.0, "caudal": 279.0}, {"timestamp": "2024-07-30 16:58:03", "planta": "Planta 1", "compresor1": "En l\u00ednea", "compresor2": "Off", "temp_secador_1": 18.8, "humedad_secador_1": 75.6, "temp_secador_2": NaN, "humedad_secador_2": NaN, "pureza_oxigeno": 282.0, "presion_linea": 282.0, "caudal": 280.0}, {"timestamp": "2024-07-30 16:58:04", "planta": "Planta 1", "compresor1": "En l\u00ednea", "compresor2": "Off", "temp_secador_1": 18.8, "humedad_secador_1": 75.5, "temp_secador_2": NaN, "humedad_secador_2": NaN, "pureza_oxigeno": 284.0, "presion_linea": 285.0, "caudal": 282.0}, {"timestamp": "2024-07-30 16:58:05", "planta": "Planta 1", "compresor1": "En l\u00ednea", "compresor2": "Off", "temp_secador_1": 18.8, "humedad_secador_1": 75.5, "temp_secador_2": NaN, "humedad_secador_2": NaN, "pureza_oxigeno": 280.0, "presion_linea": 281.0, "caudal": 279.0}, {"timestamp": "2024-07-30 16:58:06", "planta": "Planta 1", "compresor1": "En l\u00ednea", "compresor2": "Off", "temp_secador_1": 18.8, "humedad_secador_1": 75.7, "temp_secador_2": NaN, "humedad_secador_2": NaN, "pureza_oxigeno": 291.0, "presion_linea": 293.0, "caudal": 289.0}, {"timestamp": "2024-07-30 16:58:07", "planta": "Planta 1", "compresor1": "En l\u00ednea", "compresor2": "Off", "temp_secador_1": 18.8, "humedad_secador_1": 75.7, "temp_secador_2": NaN, "humedad_secador_2": NaN, "pureza_oxigeno": 285.0, "presion_linea": 285.0, "caudal": 283.0}, {"timestamp": "2024-07-30 16:58:08", "planta": "Planta 1", "compresor1": "En l\u00ednea", "compresor2": "Off", "temp_secador_1": 18.8, "humedad_secador_1": 75.6, "temp_secador_2": NaN, "humedad_secador_2": NaN, "pureza_oxigeno": 282.0, "presion_linea": 282.0, "caudal": 281.0}, {"timestamp": "2024-07-30 16:58:09", "planta": "Planta 1", "compresor1": "En l\u00ednea", "compresor2": "Off", "temp_secador_1": 18.8, "humedad_secador_1": 75.6, "temp_secador_2": NaN, "humedad_secador_2": NaN, "pureza_oxigeno": 291.0, "presion_linea": 293.0, "caudal": 289.0}, {"timestamp": "2024-07-30 16:58:10", "planta": "Planta 1", "compresor1": "En l\u00ednea", "compresor2": "Off", "temp_secador_1": 18.7, "humedad_secador_1": 75.9, "temp_secador_2": NaN, "humedad_secador_2": NaN, "pureza_oxigeno": 281.0, "presion_linea": 280.0, "caudal": 279.0}, {"timestamp": "2024-07-30 16:58:11", "planta": "Planta 1", "compresor1": "En l\u00ednea", "compresor2": "Off", "temp_secador_1": 18.7, "humedad_secador_1": 75.9, "temp_secador_2": NaN, "humedad_secador_2": NaN, "pureza_oxigeno": 282.0, "presion_linea": 282.0, "caudal": 280.0}, {"timestamp": "2024-07-30 16:58:12", "planta": "Planta 1", "compresor1": "En l\u00ednea", "compresor2": "Off", "temp_secador_1": 18.8, "humedad_secador_1": 75.3, "temp_secador_2": NaN, "humedad_secador_2": NaN, "pureza_oxigeno": 283.0, "presion_linea": 284.0, "caudal": 281.0}, {"timestamp": "2024-07-30 16:58:13", "planta": "Planta 1", "compresor1": "En l\u00ednea", "compresor2": "Off", "temp_secador_1": 18.8, "humedad_secador_1": 75.3, "temp_secador_2": NaN, "humedad_secador_2": NaN, "pureza_oxigeno": 280.0, "presion_linea": 281.0, "caudal": 279.0}, {"timestamp": "2024-07-30 16:58:14", "planta": "Planta 1", "compresor1": "En l\u00ednea", "compresor2": "Off", "temp_secador_1": 18.9, "humedad_secador_1": 75.9, "temp_secador_2": NaN, "humedad_secador_2": NaN, "pureza_oxigeno": 290.0, "presion_linea": 292.0, "caudal": 289.0}, {"timestamp": "2024-07-30 16:58:15", "planta": "Planta 1", "compresor1": "En l\u00ednea", "compresor2": "Off", "temp_secador_1": 18.9, "humedad_secador_1": 75.9, "temp_secador_2": NaN, "humedad_secador_2": NaN, "pureza_oxigeno": 287.0, "presion_linea": 287.0, "caudal": 285.0}, {"timestamp": "2024-07-30 16:58:16", "planta": "Planta 1", "compresor1": "En l\u00ednea", "compresor2": "Off", "temp_secador_1": 18.8, "humedad_secador_1": 75.3, "temp_secador_2": NaN, "humedad_secador_2": NaN, "pureza_oxigeno": 281.0, "presion_linea": 281.0, "caudal": 280.0}, {"timestamp": "2024-07-30 16:58:17", "planta": "Planta 1", "compresor1": "En l\u00ednea", "compresor2": "Off", "temp_secador_1": 18.8, "humedad_secador_1": 75.3, "temp_secador_2": NaN, "humedad_secador_2": NaN, "pureza_oxigeno": 289.0, "presion_linea": 290.0, "caudal": 287.0}, {"timestamp": "2024-07-30 16:58:18", "planta": "Planta 1", "compresor1": "En l\u00ednea", "compresor2": "Off", "temp_secador_1": 18.8, "humedad_secador_1": 75.6, "temp_secador_2": NaN, "humedad_secador_2": NaN, "pureza_oxigeno": 282.0, "presion_linea": 282.0, "caudal": 281.0}, {"timestamp": "2024-07-30 16:58:19", "planta": "Planta 1", "compresor1": "En l\u00ednea", "compresor2": "Off", "temp_secador_1": 18.8, "humedad_secador_1": 75.6, "temp_secador_2": NaN, "humedad_secador_2": NaN, "pureza_oxigeno": 281.0, "presion_linea": 280.0, "caudal": 279.0}, {"timestamp": "2024-07-30 16:58:20", "planta": "Planta 1", "compresor1": "En l\u00ednea", "compresor2": "Off", "temp_secador_1": 18.8, "humedad_secador_1": 75.2, "temp_secador_2": NaN, "humedad_secador_2": NaN, "pureza_oxigeno": 291.0, "presion_linea": 293.0, "caudal": 289.0}, {"timestamp": "2024-07-30 16:58:21", "planta": "Planta 1", "compresor1": "En l\u00ednea", "compresor2": "Off", "temp_secador_1": 18.8, "humedad_secador_1": 75.2, "temp_secador_2": NaN, "humedad_secador_2": NaN, "pureza_oxigeno": 286.0, "presion_linea": 286.0, "caudal": 284.0}, {"timestamp": "2024-07-30 16:58:22", "planta": "Planta 1", "compresor1": "En l\u00ednea", "compresor2": "Off", "temp_secador_1": 18.8, "humedad_secador_1": 75.5, "temp_secador_2": NaN, "humedad_secador_2": NaN, "pureza_oxigeno": 281.0, "presion_linea": 281.0, "caudal": 280.0}, {"timestamp": "2024-07-30 16:58:23", "planta": "Planta 1", "compresor1": "En l\u00ednea", "compresor2": "Off", "temp_secador_1": 18.8, "humedad_secador_1": 75.5, "temp_secador_2": NaN, "humedad_secador_2": NaN, "pureza_oxigeno": 288.0, "presion_linea": 290.0, "caudal": 286.0}]